<?xml version="1.0" encoding="UTF-8"?>

<faces-config
    xmlns="http://java.sun.com/xml/ns/javaee"
    xmlns:xsi="http://www.w3.org/2001/XMLSchema-instance"
    xsi:schemaLocation="http://java.sun.com/xml/ns/javaee http://java.sun.com/xml/ns/javaee/web-facesconfig_2_0.xsd"
    version="2.0">

    <managed-bean>
		<managed-bean-name>pt_genelDb</managed-bean-name>
		<managed-bean-class>tools.GenelDb</managed-bean-class>
		<managed-bean-scope>request</managed-bean-scope>
	</managed-bean>
	<managed-bean>
		<managed-bean-name>pc_Kul_list</managed-bean-name>
		<managed-bean-class>pagecode.pages.admin.include.Kul_list</managed-bean-class>
		<managed-bean-scope>request</managed-bean-scope>
	</managed-bean>
	<managed-bean>
		<managed-bean-name>KulT1plerManager</managed-bean-name>
		<managed-bean-class>entities.kullanicilar.controller.KulT1plerManager</managed-bean-class>
		<managed-bean-scope>request</managed-bean-scope>
	</managed-bean>
	<managed-bean>
		<managed-bean-name>KulDurumlarManager</managed-bean-name>
		<managed-bean-class>entities.kullanicilar.controller.KulDurumlarManager</managed-bean-class>
		<managed-bean-scope>request</managed-bean-scope>
	</managed-bean>
	<managed-bean>
		<managed-bean-name>KulYetk1lerManager</managed-bean-name>
		<managed-bean-class>entities.kullanicilar.controller.KulYetk1lerManager</managed-bean-class>
		<managed-bean-scope>request</managed-bean-scope>
	</managed-bean>
	<managed-bean>
		<managed-bean-name>pc_global_kul_tools</managed-bean-name>
		<managed-bean-class>pagecode.pages.admin.include.Global_kul_tools</managed-bean-class>
		<managed-bean-scope>session</managed-bean-scope>
	</managed-bean>
	<managed-bean>
		<managed-bean-name>Kullan1c1larManager</managed-bean-name>
		<managed-bean-class>entities.kullanicilar.controller.Kullan1c1larManager</managed-bean-class>
		<managed-bean-scope>request</managed-bean-scope>
	</managed-bean>
	<managed-bean>
		<managed-bean-name>pc_Kul_ekle</managed-bean-name>
		<managed-bean-class>pagecode.pages.admin.include.Kul_ekle</managed-bean-class>
		<managed-bean-scope>request</managed-bean-scope>
	</managed-bean>
	<managed-bean>
		<managed-bean-name>pc_Kul_duzelt</managed-bean-name>
		<managed-bean-class>pagecode.pages.admin.include.Kul_duzelt</managed-bean-class>
		<managed-bean-scope>request</managed-bean-scope>
	</managed-bean>
	<managed-bean>
		<managed-bean-name>pc_sessionBean</managed-bean-name>
		<managed-bean-class>pagecode.pages.login.Login_frm</managed-bean-class>
		<managed-bean-scope>session</managed-bean-scope>
	</managed-bean>
	<managed-bean>
		<managed-bean-name>K1taplarManager</managed-bean-name>
		<managed-bean-class>entities.yayin.controller.K1taplarManager</managed-bean-class>
		<managed-bean-scope>request</managed-bean-scope>
	</managed-bean>
	<managed-bean>
		<managed-bean-name>pc_Ktp_ekle</managed-bean-name>
		<managed-bean-class>pagecode.pages.admin.include.Ktp_ekle</managed-bean-class>
		<managed-bean-scope>session</managed-bean-scope>
	</managed-bean>
	<managed-bean>
		<managed-bean-name>pc_Drg_ekle</managed-bean-name>
		<managed-bean-class>pagecode.pages.admin.include.Drg_ekle</managed-bean-class>
		<managed-bean-scope>session</managed-bean-scope>
	</managed-bean>
	<managed-bean>
		<managed-bean-name>Derg1lerManager</managed-bean-name>
		<managed-bean-class>entities.yayin.controller.Derg1lerManager</managed-bean-class>
		<managed-bean-scope>request</managed-bean-scope>
	</managed-bean>
	<managed-bean>
		<managed-bean-name>pc_Ktp_list</managed-bean-name>
		<managed-bean-class>pagecode.pages.admin.include.Ktp_list</managed-bean-class>
		<managed-bean-scope>request</managed-bean-scope>
	</managed-bean>
	<managed-bean>
		<managed-bean-name>pc_Drg_list</managed-bean-name>
		<managed-bean-class>pagecode.pages.admin.include.Drg_list</managed-bean-class>
		<managed-bean-scope>request</managed-bean-scope>
	</managed-bean>
	<managed-bean>
		<managed-bean-name>pc_Ktp_duzelt</managed-bean-name>
		<managed-bean-class>pagecode.pages.admin.include.Ktp_duzelt</managed-bean-class>
		<managed-bean-scope>request</managed-bean-scope>
	</managed-bean>
	<managed-bean>
		<managed-bean-name>pc_Drg_duzelt</managed-bean-name>
		<managed-bean-class>pagecode.pages.admin.include.Drg_duzelt</managed-bean-class>
		<managed-bean-scope>request</managed-bean-scope>
	</managed-bean>
	<managed-bean>
		<managed-bean-name>Yay1nlarRegManager</managed-bean-name>
		<managed-bean-class>entities.yayin.controller.Yay1nlarRegManager</managed-bean-class>
		<managed-bean-scope>request</managed-bean-scope>
	</managed-bean>
	<managed-bean>
		<managed-bean-name>Yay1nlarManager</managed-bean-name>
		<managed-bean-class>entities.yayin.controller.Yay1nlarManager</managed-bean-class>
		<managed-bean-scope>request</managed-bean-scope>
	</managed-bean>
	<managed-bean>
		<managed-bean-name>pc_YayinArama</managed-bean-name>
		<managed-bean-class>pagecode.pages.YayinArama</managed-bean-class>
		<managed-bean-scope>request</managed-bean-scope>
	</managed-bean>
	<managed-bean>
		<managed-bean-name>pc_Arama</managed-bean-name>
		<managed-bean-class>pagecode.pages.include.Arama</managed-bean-class>
		<managed-bean-scope>session</managed-bean-scope>
	</managed-bean>
	<managed-bean>
		<managed-bean-name>pc_ABar</managed-bean-name>
		<managed-bean-class>pagecode.pages.include.AramaBar</managed-bean-class>
		<managed-bean-scope>request</managed-bean-scope>
	</managed-bean>
	<managed-bean>
		<managed-bean-name>pc_Yyn_hareket</managed-bean-name>
		<managed-bean-class>pagecode.pages.admin.include.Yyn_hareket</managed-bean-class>
		<managed-bean-scope>request</managed-bean-scope>
	</managed-bean>
	<managed-bean>
		<managed-bean-name>pc_Yyn_istek_yonet</managed-bean-name>
		<managed-bean-class>pagecode.pages.admin.include.Kul_istek_yonet</managed-bean-class>
		<managed-bean-scope>request</managed-bean-scope>
	</managed-bean>
	<managed-bean>
		<managed-bean-name>YynHareketManager</managed-bean-name>
		<managed-bean-class>entities.yayin.controller.YynHareketManager</managed-bean-class>
		<managed-bean-scope>request</managed-bean-scope>
	</managed-bean>
	<managed-bean>
		<managed-bean-name>D1llerManager</managed-bean-name>
		<managed-bean-class>entities.yayinTools.controller.D1llerManager</managed-bean-class>
		<managed-bean-scope>request</managed-bean-scope>
	</managed-bean>
	<managed-bean>
		<managed-bean-name>KonularManager</managed-bean-name>
		<managed-bean-class>entities.yayinTools.controller.KonularManager</managed-bean-class>
		<managed-bean-scope>request</managed-bean-scope>
	</managed-bean>
	<managed-bean>
		<managed-bean-name>Yay1nc1larManager</managed-bean-name>
		<managed-bean-class>entities.yayinTools.controller.Yay1nc1larManager</managed-bean-class>
		<managed-bean-scope>request</managed-bean-scope>
	</managed-bean>
	<managed-bean>
		<managed-bean-name>Yay1nlarRegManager1</managed-bean-name>
		<managed-bean-class>entities.yayin.controller.Yay1nlarRegManager</managed-bean-class>
		<managed-bean-scope>request</managed-bean-scope>
	</managed-bean>
	<managed-bean>
		<managed-bean-name>YynAyr1nt1RegManager</managed-bean-name>
		<managed-bean-class>entities.yayin.controller.YynAyr1nt1RegManager</managed-bean-class>
		<managed-bean-scope>request</managed-bean-scope>
	</managed-bean>
	<managed-bean>
		<managed-bean-name>AltT1plerManager</managed-bean-name>
		<managed-bean-class>entities.yayinTools.controller.AltT1plerManager</managed-bean-class>
		<managed-bean-scope>request</managed-bean-scope>
	</managed-bean>
	<managed-bean>
		<managed-bean-name>KutuphaneManager</managed-bean-name>
		<managed-bean-class>entities.yayinTools.controller.KutuphaneManager</managed-bean-class>
		<managed-bean-scope>request</managed-bean-scope>
	</managed-bean>
	<managed-bean>
		<managed-bean-name>YynFormatManager</managed-bean-name>
		<managed-bean-class>entities.yayinTools.controller.YynFormatManager</managed-bean-class>
		<managed-bean-scope>request</managed-bean-scope>
	</managed-bean>
	<managed-bean>
		<managed-bean-name>YynSek1lManager</managed-bean-name>
		<managed-bean-class>entities.yayinTools.controller.YynSek1lManager</managed-bean-class>
		<managed-bean-scope>request</managed-bean-scope>
	</managed-bean>
	<managed-bean>
		<managed-bean-name>KtphnBolumManager</managed-bean-name>
		<managed-bean-class>entities.yayinTools.controller.KtphnBolumManager</managed-bean-class>
		<managed-bean-scope>request</managed-bean-scope>
	</managed-bean>
	<managed-bean>
		<managed-bean-name>Yyn1z1nlerManager</managed-bean-name>
		<managed-bean-class>entities.yayinTools.controller.Yyn1z1nlerManager</managed-bean-class>
		<managed-bean-scope>request</managed-bean-scope>
	</managed-bean>
	<managed-bean>
		<managed-bean-name>pc_Yyn_Goster</managed-bean-name>
		<managed-bean-class>pagecode.pages.user.include.Yyn_Goster</managed-bean-class>
		<managed-bean-scope>request</managed-bean-scope>
	</managed-bean>
	<managed-bean>
		<managed-bean-name>pc_Kul_Profil</managed-bean-name>
		<managed-bean-class>pagecode.pages.user.include.Kul_Profil</managed-bean-class>
		<managed-bean-scope>request</managed-bean-scope>
	</managed-bean>
	<managed-bean>
		<managed-bean-name>pc_Yyn_Listem</managed-bean-name>
		<managed-bean-class>pagecode.pages.user.include.Yyn_Listem</managed-bean-class>
		<managed-bean-scope>request</managed-bean-scope>
	</managed-bean>
	<managed-bean>
		<managed-bean-name>pc_Kul_istek</managed-bean-name>
		<managed-bean-class>pagecode.pages.user.include.Kul_istek</managed-bean-class>
		<managed-bean-scope>request</managed-bean-scope>
	</managed-bean>
	<managed-bean>
		<managed-bean-name>pc_Kul_index</managed-bean-name>
		<managed-bean-class>pagecode.pages.user.include.Kul_index</managed-bean-class>
		<managed-bean-scope>request</managed-bean-scope>
	</managed-bean>
	<managed-bean>
		<managed-bean-name>KulYynHareketManager</managed-bean-name>
		<managed-bean-class>entities.yayin.controller.KulYynHareketManager</managed-bean-class>
		<managed-bean-scope>request</managed-bean-scope>
	</managed-bean>
	<managed-bean>
		<managed-bean-name>Yay1nlarManager1</managed-bean-name>
		<managed-bean-class>entities.yayin.controller.Yay1nlarManager1</managed-bean-class>
		<managed-bean-scope>request</managed-bean-scope>
	</managed-bean>
	<managed-bean>
		<managed-bean-name>Yay1nlarManager2</managed-bean-name>
		<managed-bean-class>entities.yayin.controller.Yay1nlarManager2</managed-bean-class>
		<managed-bean-scope>request</managed-bean-scope>
	</managed-bean>
	<managed-bean>
		<managed-bean-name>Yay1nRezerveRegManager</managed-bean-name>
		<managed-bean-class>entities.yayin.controller.Yay1nRezerveRegManager</managed-bean-class>
		<managed-bean-scope>request</managed-bean-scope>
	</managed-bean>
	<managed-bean>
		<managed-bean-name>Yay1nRezerveManager</managed-bean-name>
		<managed-bean-class>entities.yayin.controller.Yay1nRezerveManager</managed-bean-class>
		<managed-bean-scope>request</managed-bean-scope>
	</managed-bean>
	<managed-bean>
		<managed-bean-name>L1stemRegManager</managed-bean-name>
		<managed-bean-class>entities.yayin.controller.L1stemRegManager</managed-bean-class>
		<managed-bean-scope>request</managed-bean-scope>
	</managed-bean>
	<managed-bean>
		<managed-bean-name>L1stemManager</managed-bean-name>
		<managed-bean-class>entities.yayin.controller.L1stemManager</managed-bean-class>
		<managed-bean-scope>request</managed-bean-scope>
	</managed-bean>
	<managed-bean>
		<managed-bean-name>Kul1steklerRegManager</managed-bean-name>
		<managed-bean-class>entities.yayin.controller.Kul1steklerRegManager</managed-bean-class>
		<managed-bean-scope>request</managed-bean-scope>
	</managed-bean>
	<managed-bean>
		<managed-bean-name>YynHareket4istatManager</managed-bean-name>
		<managed-bean-class>entities.yayin.controller.YynHareket4istatManager</managed-bean-class>
		<managed-bean-scope>request</managed-bean-scope>
	</managed-bean>
	<navigation-rule>
		<from-view-id>*</from-view-id>
		<navigation-case>
		<from-outcome>unauthorizedPage</from-outcome>
		<to-view-id>/errorPages/unauthorized.xhtml</to-view-id>
		<redirect/>
		</navigation-case>
	</navigation-rule>
	<navigation-rule>
		<navigation-case>
		<from-outcome>gitDuzeltFrm</from-outcome>
		<to-view-id>/pages/admin/admin_kul_duzelt.xhtml</to-view-id>
		<redirect/>
		</navigation-case>
	</navigation-rule>
	<navigation-rule>		
		<navigation-case>
		<from-outcome>gitKtpDuzelt</from-outcome>
		<to-view-id>/pages/admin/admin_ktp_duzelt.xhtml</to-view-id>
		<redirect/>
		</navigation-case>
	</navigation-rule>
	<navigation-rule>
		<navigation-case>
		<from-outcome>gitDrgDuzelt</from-outcome>
		<to-view-id>/pages/admin/admin_drg_duzelt.xhtml</to-view-id>
		<redirect/>
		</navigation-case>
	</navigation-rule>
	<navigation-rule>
		<from-view-id>*</from-view-id>
		<navigation-case>
		<from-outcome>Admin</from-outcome>
		<to-view-id>/pages/index.xhtml</to-view-id>
		</navigation-case>
	</navigation-rule>
	<navigation-rule>
		<from-view-id>*</from-view-id>
		<navigation-case>
		<from-outcome>gitListFrm</from-outcome>
		<to-view-id>/pages/admin/admin_kul_list.xhtml</to-view-id>
		</navigation-case>
	</navigation-rule>
	<navigation-rule>
		<navigation-case>
			<from-outcome>loginPage</from-outcome>
			<to-view-id>/pages/login/login.xhtml</to-view-id>
			<redirect/>
		</navigation-case>
	</navigation-rule>
	<navigation-rule>
		<navigation-case>
			<from-outcome>indexUser</from-outcome>
			<to-view-id>/pages/user/index.xhtml</to-view-id>
			<redirect/>
		</navigation-case>
	</navigation-rule>
	<navigation-rule>
		<navigation-case>
			<from-outcome>indexAdmin</from-outcome>
			<to-view-id>/pages/admin/index.xhtml</to-view-id>
			<redirect/>
		</navigation-case>
	</navigation-rule>
	
	<navigation-rule>
		<navigation-case>
			<from-outcome>index</from-outcome>
			<to-view-id>/pages/index.xhtml</to-view-id>
			<redirect/>
		</navigation-case>
	</navigation-rule>
	<navigation-rule>
		<navigation-case>
			<from-outcome>UserProfile</from-outcome>
			<to-view-id>/pages/user/user_Profil.xhtml</to-view-id>
			<redirect/>
		</navigation-case>
	</navigation-rule>
	<navigation-rule>
		<navigation-case>
			<from-outcome>UserUzeri</from-outcome>
			<to-view-id>/pages/user/user_Uzerimdekiler.xhtml</to-view-id>
			<redirect/>
		</navigation-case>
	</navigation-rule>
	<navigation-rule>
		<navigation-case>
			<from-outcome>UserIade</from-outcome>
			<to-view-id>/pages/user/user_Iadelerim.xhtml</to-view-id>
			<redirect/>
		</navigation-case>
	</navigation-rule>
	<navigation-rule>
		<navigation-case>
			<from-outcome>UserRezerv</from-outcome>
			<to-view-id>/pages/user/user_Rezerv.xhtml</to-view-id>
			<redirect/>
		</navigation-case>
	</navigation-rule>
	<navigation-rule>
		<navigation-case>
			<from-outcome>UserListem</from-outcome>
			<to-view-id>/pages/user/user_Listem.xhtml</to-view-id>
			<redirect/>
		</navigation-case>
	</navigation-rule>
		<navigation-rule>
		<navigation-case>
			<from-outcome>User1stek</from-outcome>
			<to-view-id>/pages/user/user_isteklerim.xhtml</to-view-id>
			<redirect/>
		</navigation-case>
	</navigation-rule>
	<lifecycle>
		<phase-listener>devendr.AccessControlPhaseListener</phase-listener>
	</lifecycle>
	<validator>
		<validator-id>EmailValidator</validator-id>
		<validator-class>tools.EmailValidator</validator-class>
	</validator>
</faces-config>